espresso_mcp/__init__.py
espresso_mcp/server.py
espresso_mcp-0.1.6.dist-info/METADATA
espresso_mcp-0.1.6.dist-info/WHEEL
espresso_mcp-0.1.6.dist-info/entry_points.txt
espresso_mcp-0.1.6.dist-info/licenses/LICENSE
espresso_mcp-0.1.6.dist-info/RECORD
