Metadata-Version: 2.4
Name: espresso-mcp
Version: 0.1.6
Summary: An MCP Server for the Espresso Android Test Framework
License-File: LICENSE
Requires-Python: >=3.10
Requires-Dist: httpx>=0.28.1
Requires-Dist: mcp[cli]>=1.7.1
Requires-Dist: pillow>=11.2.1
